django_giftbox-0.1.1.dist-info/DESCRIPTION.rst
django_giftbox-0.1.1.dist-info/METADATA
django_giftbox-0.1.1.dist-info/RECORD
django_giftbox-0.1.1.dist-info/WHEEL
django_giftbox-0.1.1.dist-info/metadata.json
django_giftbox-0.1.1.dist-info/top_level.txt
giftbox/__init__.py
giftbox/box.py
giftbox/tests.py
giftbox/testsettings.py
giftbox/version.py
giftbox/wrappers.py
