Metadata-Version: 2.0
Name: django-giftbox
Version: 0.1.1
Summary: A package that includes xsendfile capabilities for Django
Home-page: https://github.com/bwhicks/django-giftbox
Author: Benjamin Hicks
Author-email: benajmin.w.hicks@gmail.com
License: MIT
Keywords: sendfile,apache
Platform: UNKNOWN
Classifier: Development Status :: 3 - Alpha
Classifier: Intended Audience :: Developers
Classifier: License :: OSI Approved :: MIT License
Classifier: Programming Language :: Python :: 2
Classifier: Programming Language :: Python :: 2.7
Classifier: Programming Language :: Python :: 3
Classifier: Programming Language :: Python :: 3.6
Classifier: Programming Language :: Python :: 3.7
Classifier: Framework :: Django
Classifier: Framework :: Django :: 2.2
Classifier: Framework :: Django :: 1.11
Classifier: Framework :: Django :: 1.8
Requires-Dist: django (>=1.8)
Provides-Extra: develop
Requires-Dist: pytest; extra == 'develop'
Requires-Dist: pytest-django; extra == 'develop'
Requires-Dist: pytest-cov; extra == 'develop'
Requires-Dist: mock; extra == 'develop'
Requires-Dist: python-magic; extra == 'develop'
Requires-Dist: tox; extra == 'develop'
Requires-Dist: tox-travis; extra == 'develop'
Requires-Dist: twine; extra == 'develop'
Provides-Extra: magic
Requires-Dist: python-magic; extra == 'magic'
Provides-Extra: test
Requires-Dist: pytest; extra == 'test'
Requires-Dist: pytest-django; extra == 'test'
Requires-Dist: pytest-cov; extra == 'test'
Requires-Dist: mock; extra == 'test'
Requires-Dist: python-magic; extra == 'test'
Requires-Dist: tox; extra == 'test'
Requires-Dist: tox-travis; extra == 'test'
